fastapi_auto_router/__init__.py
fastapi_auto_router/router_loader.py
fastapi_auto_router-0.2.2.dist-info/METADATA
fastapi_auto_router-0.2.2.dist-info/WHEEL
fastapi_auto_router-0.2.2.dist-info/licenses/LICENSE
fastapi_auto_router-0.2.2.dist-info/RECORD
