Metadata-Version: 2.4
Name: fastapi-auto-router
Version: 0.2.2
Summary: Automatic router configuration for FastAPI based on filesystem structure
Project-URL: Homepage, https://github.com/forchain/fastapi-auto-router
Project-URL: Documentation, https://github.com/forchain/fastapi-auto-router#readme
Project-URL: Repository, https://github.com/forchain/fastapi-auto-router.git
Project-URL: Issues, https://github.com/forchain/fastapi-auto-router/issues
Author-email: Tony Outlier <Outlier@Chainer.Tech>
License: MIT
License-File: LICENSE
Keywords: automatic,configuration,fastapi,router
Classifier: Development Status :: 4 - Beta
Classifier: Framework :: FastAPI
Classifier: Intended Audience :: Developers
Classifier: License :: OSI Approved :: MIT License
Classifier: Programming Language :: Python
Classifier: Programming Language :: Python :: 3
Classifier: Programming Language :: Python :: 3.7
Classifier: Programming Language :: Python :: 3.8
Classifier: Programming Language :: Python :: 3.9
Classifier: Programming Language :: Python :: 3.10
Classifier: Programming Language :: Python :: 3.11
Classifier: Topic :: Internet :: WWW/HTTP
Classifier: Topic :: Software Development :: Libraries :: Python Modules
Requires-Python: >=3.7
Requires-Dist: fastapi>=0.68.0
